django_database_constraints/__init__.py
django_database_constraints/forms.py
django_database_constraints/models.py
django_database_constraints/tests.py
django_database_constraints/views.py
django_database_constraints-2.0.dist-info/DESCRIPTION.rst
django_database_constraints-2.0.dist-info/METADATA
django_database_constraints-2.0.dist-info/RECORD
django_database_constraints-2.0.dist-info/WHEEL
django_database_constraints-2.0.dist-info/metadata.json
django_database_constraints-2.0.dist-info/top_level.txt
