Metadata-Version: 2.0
Name: django-database-constraints
Version: 2.0
Summary: Django library for more easily working with transactions and constraints in Forms, ModelForms and the Views that use them.
Home-page: https://github.com/jaylett/django-database-constraints
Author: James Aylett
Author-email: james@tartarus.org
License: MIT
Platform: UNKNOWN
Classifier: Intended Audience :: Developers
Classifier: Framework :: Django
Classifier: License :: OSI Approved :: MIT License
Classifier: Programming Language :: Python :: 2
Classifier: Programming Language :: Python :: 3
Requires-Dist: Django (>=1.10.3)
